CHANGES.txt
README.txt
setup.cfg
setup.py
docs/HISTORY.txt
docs/INSTALL.txt
docs/LICENSE.GPL
docs/LICENSE.txt
zgeo/__init__.py
zgeo.plone.kml.egg-info/PKG-INFO
zgeo.plone.kml.egg-info/SOURCES.txt
zgeo.plone.kml.egg-info/dependency_links.txt
zgeo.plone.kml.egg-info/entry_points.txt
zgeo.plone.kml.egg-info/namespace_packages.txt
zgeo.plone.kml.egg-info/not-zip-safe
zgeo.plone.kml.egg-info/requires.txt
zgeo.plone.kml.egg-info/top_level.txt
zgeo/plone/__init__.py
zgeo/plone/kml/README.txt
zgeo/plone/kml/__init__.py
zgeo/plone/kml/browser.py
zgeo/plone/kml/configure.zcml
zgeo/plone/kml/setuphandlers.py
zgeo/plone/kml/version.txt
zgeo/plone/kml/Extensions/Install.py
zgeo/plone/kml/Extensions/__init__.py
zgeo/plone/kml/profiles/default/import_steps.xml
zgeo/plone/kml/profiles/default/zgeo.plone.kml_various.txt
zgeo/plone/kml/tests/__init__.py
zgeo/plone/kml/tests/base.py
zgeo/plone/kml/tests/kml-docs.txt
zgeo/plone/kml/tests/large-folder-kml.txt
zgeo/plone/kml/tests/test_doctests.py
zgeo/plone/kml/tests/test_setup.py
