Metadata-Version: 1.0
Name: zgeo.plone.kml
Version: 0.1.2
Summary: KML for Plone content
Home-page: http://trac.gispython.org/projects/PrimaGIS/wiki/zgeo.plone.kml
Author: Sean Gillies
Author-email: sgillies@frii.com
License: GPL
Keywords: plone geo gis kml google earth
Platform: UNKNOWN
Classifier: Framework :: Plone
Classifier: Framework :: Zope2
Classifier: Framework :: Zope3
Classifier: Programming Language :: Python
Classifier: Topic :: Software Development :: Libraries :: Python Modules
Classifier: Topic :: Scientific/Engineering :: GIS
Classifier: Development Status :: 3 - Alpha
Classifier: Intended Audience :: Developers
